schwabdev/__init__.py
schwabdev/client.py
schwabdev/enums.py
schwabdev/stream.py
schwabdev/tokens.py
schwabdev/translate.py
schwabdev-3.0.1.dist-info/licenses/LICENSE.txt
schwabdev-3.0.1.dist-info/METADATA
schwabdev-3.0.1.dist-info/WHEEL
schwabdev-3.0.1.dist-info/top_level.txt
schwabdev-3.0.1.dist-info/RECORD
