Metadata-Version: 2.4
Name: schwabdev
Version: 3.0.1
Summary: An easy and lightweight wrapper for using the Charles Schwab API.
Author-email: Tyler Bowers <tylerebowers@gmail.com>
License-Expression: MIT
Project-URL: Homepage, https://github.com/tylerebowers/Schwabdev
Project-URL: Documentation, https://tylerebowers.github.io/Schwabdev/
Project-URL: Source, https://github.com/tylerebowers/Schwabdev
Project-URL: Youtube, https://www.youtube.com/playlist?list=PLs4JLWxBQIxpbvCj__DjAc0RRTlBz-TR8
Project-URL: PyPI, https://pypi.org/project/schwabdev/
Keywords: python,schwab,api,client,finance,trading,stocks,equities,options,forex,futures
Classifier: Topic :: Office/Business :: Financial :: Investment
Classifier: Development Status :: 5 - Production/Stable
Classifier: Programming Language :: Python :: 3
Classifier: Operating System :: OS Independent
Classifier: Intended Audience :: Developers
Classifier: Natural Language :: English
Requires-Python: >=3.11
License-File: LICENSE.txt
Requires-Dist: tzdata
Requires-Dist: aiohttp
Requires-Dist: requests
Requires-Dist: websockets
Requires-Dist: cryptography
Dynamic: license-file
